AUTHORS.txt
CHANGES.rst
CLASSIFIERS.txt
LICENSE
MANIFEST.in
README.rst
REQUIREMENTS.txt
setup.py
flask_bluestatic/__init__.py
flask_bluestatic/__init__.pyc
flask_bluestatic/main.py
flask_bluestatic/main.pyc
flask_bluestatic.egg-info/PKG-INFO
flask_bluestatic.egg-info/SOURCES.txt
flask_bluestatic.egg-info/dependency_links.txt
flask_bluestatic.egg-info/requires.txt
flask_bluestatic.egg-info/top_level.txt
test/test.py